astromol/__init__.py
astromol/functions.py
astromol/molecules.py
astromol/references.py
astromol/sources.py
astromol/telescopes.py
astromol/bibtex/exgal_refs.bib
astromol/bibtex/exo_refs.bib
astromol/bibtex/ice_refs.bib
astromol/bibtex/ppd_refs.bib
astromol-2021.7.dist-info/METADATA
astromol-2021.7.dist-info/WHEEL
astromol-2021.7.dist-info/top_level.txt
astromol-2021.7.dist-info/RECORD
