Metadata-Version: 2.1
Name: astromol
Version: 2021.7
Summary: A Database of Molecules Detected in Space
Author: Brett A. McGuire (Department of Chemistry, Massachusetts Institute of Technology)
License: MIT
Requires-Dist: bibtexparser
Requires-Dist: numpy
Requires-Dist: rdkit-pypi
Requires-Dist: matplotlib
Requires-Dist: colour
Requires-Dist: seaborn
Requires-Dist: scipy
Requires-Dist: datetime
Requires-Dist: python-pptx
Requires-Dist: periodictable
Provides-Extra: dev
Requires-Dist: twine (>=4.0.2) ; extra == 'dev'
